{
  "indexes": [
    {
      "collectionGroup": "booking_requests",
      "queryScope": "COLLECTION",
      "fields": [
        { "fieldPath": "masterUid", "order": "ASCENDING" },
        { "fieldPath": "preferredDate", "order": "ASCENDING" }
      ]
    },
    {
      "collectionGroup": "booking_requests",
      "queryScope": "COLLECTION",
      "fields": [
        { "fieldPath": "masterUid", "order": "ASCENDING" },
        { "fieldPath": "createdAt", "order": "DESCENDING" }
      ]
    },
    {
      "collectionGroup": "orders",
      "queryScope": "COLLECTION_GROUP",
      "fields": [
        { "fieldPath": "scheduledDate", "order": "ASCENDING" }
      ]
    },
    {
      "collectionGroup": "orders",
      "queryScope": "COLLECTION_GROUP",
      "fields": [
        { "fieldPath": "status", "order": "ASCENDING" },
        { "fieldPath": "scheduledDate", "order": "ASCENDING" }
      ]
    },
    {
      "collectionGroup": "booking_requests",
      "queryScope": "COLLECTION",
      "fields": [
        { "fieldPath": "status", "order": "ASCENDING" },
        { "fieldPath": "importState", "order": "ASCENDING" },
        { "fieldPath": "updatedAt", "order": "ASCENDING" }
      ]
    },
    {
      "collectionGroup": "booking_requests",
      "queryScope": "COLLECTION",
      "fields": [
        { "fieldPath": "status", "order": "ASCENDING" },
        { "fieldPath": "importState", "order": "ASCENDING" },
        { "fieldPath": "importProcessingStartedAt", "order": "ASCENDING" }
      ]
    }
  ],
  "fieldOverrides": []
}
